extrakit/__init__.py
extrakit/py.typed
extrakit-0.1.0.dist-info/WHEEL
extrakit-0.1.0.dist-info/METADATA
extrakit-0.1.0.dist-info/RECORD
