Metadata-Version: 2.3
Name: extrakit
Version: 0.1.0
Summary: Extra Kit for Python
Author: oyghen
Author-email: oyghen <oyghen@duck.com>
Requires-Python: >=3.11
